{
  "name": "FuncState",
  "package": "org.luaj.kahluafork.compiler",
  "type": "class",
  "scope": "public",
  "describe": [],
  "extends": [],
  "implements": [],
  "constructors": [
    {
      "scope": "package",
      "name": "OPCODE",
      "describe": [],
      "args": [
        "int"
      ]
    },
    {
      "scope": "package",
      "name": "A",
      "describe": [],
      "args": [
        "int"
      ]
    },
    {
      "scope": "package",
      "name": "B",
      "describe": [],
      "args": [
        "int"
      ]
    },
    {
      "scope": "package",
      "name": "C",
      "describe": [],
      "args": [
        "int"
      ]
    },
    {
      "scope": "package",
      "name": "Bx",
      "describe": [],
      "args": [
        "int"
      ]
    },
    {
      "scope": "package",
      "name": "sBx",
      "describe": [],
      "args": [
        "int"
      ]
    }
  ],
  "fields": [
    {
      "name": "java",
      "scope": "package",
      "type": "public",
      "describe": []
    },
    {
      "name": "java",
      "scope": "package",
      "type": "public",
      "describe": []
    },
    {
      "name": "linedefined",
      "scope": "public",
      "type": "int",
      "describe": []
    },
    {
      "name": "lastlinedefined",
      "scope": "public",
      "type": "int",
      "describe": []
    },
    {
      "name": "isVararg",
      "scope": "public",
      "type": "int",
      "describe": []
    },
    {
      "name": "currentFile",
      "scope": "public",
      "type": "java.lang.String",
      "describe": [
        "static"
      ]
    },
    {
      "name": "currentfullFile",
      "scope": "public",
      "type": "java.lang.String",
      "describe": [
        "static"
      ]
    },
    {
      "name": "MAXSTACK",
      "scope": "public",
      "type": "int",
      "describe": [
        "static",
        "final"
      ]
    },
    {
      "name": "LUA_MULTRET",
      "scope": "public",
      "type": "int",
      "describe": [
        "static",
        "final"
      ]
    },
    {
      "name": "VARARG_HASARG",
      "scope": "public",
      "type": "int",
      "describe": [
        "static",
        "final"
      ]
    },
    {
      "name": "VARARG_ISVARARG",
      "scope": "public",
      "type": "int",
      "describe": [
        "static",
        "final"
      ]
    },
    {
      "name": "VARARG_NEEDSARG",
      "scope": "public",
      "type": "int",
      "describe": [
        "static",
        "final"
      ]
    },
    {
      "name": "iABC",
      "scope": "public",
      "type": "int",
      "describe": [
        "static",
        "final"
      ]
    },
    {
      "name": "iABx",
      "scope": "public",
      "type": "int",
      "describe": [
        "static",
        "final"
      ]
    },
    {
      "name": "iAsBx",
      "scope": "public",
      "type": "int",
      "describe": [
        "static",
        "final"
      ]
    },
    {
      "name": "SIZE_C",
      "scope": "public",
      "type": "int",
      "describe": [
        "static",
        "final"
      ]
    },
    {
      "name": "SIZE_B",
      "scope": "public",
      "type": "int",
      "describe": [
        "static",
        "final"
      ]
    },
    {
      "name": "SIZE_Bx",
      "scope": "public",
      "type": "int",
      "describe": [
        "static",
        "final"
      ]
    },
    {
      "name": "SIZE_A",
      "scope": "public",
      "type": "int",
      "describe": [
        "static",
        "final"
      ]
    },
    {
      "name": "SIZE_OP",
      "scope": "public",
      "type": "int",
      "describe": [
        "static",
        "final"
      ]
    },
    {
      "name": "POS_OP",
      "scope": "public",
      "type": "int",
      "describe": [
        "static",
        "final"
      ]
    },
    {
      "name": "POS_A",
      "scope": "public",
      "type": "int",
      "describe": [
        "static",
        "final"
      ]
    },
    {
      "name": "POS_C",
      "scope": "public",
      "type": "int",
      "describe": [
        "static",
        "final"
      ]
    },
    {
      "name": "POS_B",
      "scope": "public",
      "type": "int",
      "describe": [
        "static",
        "final"
      ]
    },
    {
      "name": "POS_Bx",
      "scope": "public",
      "type": "int",
      "describe": [
        "static",
        "final"
      ]
    },
    {
      "name": "MAX_OP",
      "scope": "public",
      "type": "int",
      "describe": [
        "static",
        "final"
      ]
    },
    {
      "name": "MAXARG_A",
      "scope": "public",
      "type": "int",
      "describe": [
        "static",
        "final"
      ]
    },
    {
      "name": "MAXARG_B",
      "scope": "public",
      "type": "int",
      "describe": [
        "static",
        "final"
      ]
    },
    {
      "name": "MAXARG_C",
      "scope": "public",
      "type": "int",
      "describe": [
        "static",
        "final"
      ]
    },
    {
      "name": "MAXARG_Bx",
      "scope": "public",
      "type": "int",
      "describe": [
        "static",
        "final"
      ]
    },
    {
      "name": "MAXARG_sBx",
      "scope": "public",
      "type": "int",
      "describe": [
        "static",
        "final"
      ]
    },
    {
      "name": "MASK_OP",
      "scope": "public",
      "type": "int",
      "describe": [
        "static",
        "final"
      ]
    },
    {
      "name": "MASK_A",
      "scope": "public",
      "type": "int",
      "describe": [
        "static",
        "final"
      ]
    },
    {
      "name": "MASK_B",
      "scope": "public",
      "type": "int",
      "describe": [
        "static",
        "final"
      ]
    },
    {
      "name": "MASK_C",
      "scope": "public",
      "type": "int",
      "describe": [
        "static",
        "final"
      ]
    },
    {
      "name": "MASK_Bx",
      "scope": "public",
      "type": "int",
      "describe": [
        "static",
        "final"
      ]
    },
    {
      "name": "MASK_NOT_OP",
      "scope": "public",
      "type": "int",
      "describe": [
        "static",
        "final"
      ]
    },
    {
      "name": "MASK_NOT_A",
      "scope": "public",
      "type": "int",
      "describe": [
        "static",
        "final"
      ]
    },
    {
      "name": "MASK_NOT_B",
      "scope": "public",
      "type": "int",
      "describe": [
        "static",
        "final"
      ]
    },
    {
      "name": "MASK_NOT_C",
      "scope": "public",
      "type": "int",
      "describe": [
        "static",
        "final"
      ]
    },
    {
      "name": "MASK_NOT_Bx",
      "scope": "public",
      "type": "int",
      "describe": [
        "static",
        "final"
      ]
    },
    {
      "name": "BITRK",
      "scope": "public",
      "type": "int",
      "describe": [
        "static",
        "final"
      ]
    },
    {
      "name": "MAXINDEXRK",
      "scope": "public",
      "type": "int",
      "describe": [
        "static",
        "final"
      ]
    },
    {
      "name": "NO_REG",
      "scope": "public",
      "type": "int",
      "describe": [
        "static",
        "final"
      ]
    },
    {
      "name": "OP_MOVE",
      "scope": "public",
      "type": "int",
      "describe": [
        "static",
        "final"
      ]
    },
    {
      "name": "OP_LOADK",
      "scope": "public",
      "type": "int",
      "describe": [
        "static",
        "final"
      ]
    },
    {
      "name": "OP_LOADBOOL",
      "scope": "public",
      "type": "int",
      "describe": [
        "static",
        "final"
      ]
    },
    {
      "name": "OP_LOADNIL",
      "scope": "public",
      "type": "int",
      "describe": [
        "static",
        "final"
      ]
    },
    {
      "name": "OP_GETUPVAL",
      "scope": "public",
      "type": "int",
      "describe": [
        "static",
        "final"
      ]
    },
    {
      "name": "OP_GETGLOBAL",
      "scope": "public",
      "type": "int",
      "describe": [
        "static",
        "final"
      ]
    },
    {
      "name": "OP_GETTABLE",
      "scope": "public",
      "type": "int",
      "describe": [
        "static",
        "final"
      ]
    },
    {
      "name": "OP_SETGLOBAL",
      "scope": "public",
      "type": "int",
      "describe": [
        "static",
        "final"
      ]
    },
    {
      "name": "OP_SETUPVAL",
      "scope": "public",
      "type": "int",
      "describe": [
        "static",
        "final"
      ]
    },
    {
      "name": "OP_SETTABLE",
      "scope": "public",
      "type": "int",
      "describe": [
        "static",
        "final"
      ]
    },
    {
      "name": "OP_NEWTABLE",
      "scope": "public",
      "type": "int",
      "describe": [
        "static",
        "final"
      ]
    },
    {
      "name": "OP_SELF",
      "scope": "public",
      "type": "int",
      "describe": [
        "static",
        "final"
      ]
    },
    {
      "name": "OP_ADD",
      "scope": "public",
      "type": "int",
      "describe": [
        "static",
        "final"
      ]
    },
    {
      "name": "OP_SUB",
      "scope": "public",
      "type": "int",
      "describe": [
        "static",
        "final"
      ]
    },
    {
      "name": "OP_MUL",
      "scope": "public",
      "type": "int",
      "describe": [
        "static",
        "final"
      ]
    },
    {
      "name": "OP_DIV",
      "scope": "public",
      "type": "int",
      "describe": [
        "static",
        "final"
      ]
    },
    {
      "name": "OP_MOD",
      "scope": "public",
      "type": "int",
      "describe": [
        "static",
        "final"
      ]
    },
    {
      "name": "OP_POW",
      "scope": "public",
      "type": "int",
      "describe": [
        "static",
        "final"
      ]
    },
    {
      "name": "OP_UNM",
      "scope": "public",
      "type": "int",
      "describe": [
        "static",
        "final"
      ]
    },
    {
      "name": "OP_NOT",
      "scope": "public",
      "type": "int",
      "describe": [
        "static",
        "final"
      ]
    },
    {
      "name": "OP_LEN",
      "scope": "public",
      "type": "int",
      "describe": [
        "static",
        "final"
      ]
    },
    {
      "name": "OP_CONCAT",
      "scope": "public",
      "type": "int",
      "describe": [
        "static",
        "final"
      ]
    },
    {
      "name": "OP_JMP",
      "scope": "public",
      "type": "int",
      "describe": [
        "static",
        "final"
      ]
    },
    {
      "name": "OP_EQ",
      "scope": "public",
      "type": "int",
      "describe": [
        "static",
        "final"
      ]
    },
    {
      "name": "OP_LT",
      "scope": "public",
      "type": "int",
      "describe": [
        "static",
        "final"
      ]
    },
    {
      "name": "OP_LE",
      "scope": "public",
      "type": "int",
      "describe": [
        "static",
        "final"
      ]
    },
    {
      "name": "OP_TEST",
      "scope": "public",
      "type": "int",
      "describe": [
        "static",
        "final"
      ]
    },
    {
      "name": "OP_TESTSET",
      "scope": "public",
      "type": "int",
      "describe": [
        "static",
        "final"
      ]
    },
    {
      "name": "OP_CALL",
      "scope": "public",
      "type": "int",
      "describe": [
        "static",
        "final"
      ]
    },
    {
      "name": "OP_TAILCALL",
      "scope": "public",
      "type": "int",
      "describe": [
        "static",
        "final"
      ]
    },
    {
      "name": "OP_RETURN",
      "scope": "public",
      "type": "int",
      "describe": [
        "static",
        "final"
      ]
    },
    {
      "name": "OP_FORLOOP",
      "scope": "public",
      "type": "int",
      "describe": [
        "static",
        "final"
      ]
    },
    {
      "name": "OP_FORPREP",
      "scope": "public",
      "type": "int",
      "describe": [
        "static",
        "final"
      ]
    },
    {
      "name": "OP_TFORLOOP",
      "scope": "public",
      "type": "int",
      "describe": [
        "static",
        "final"
      ]
    },
    {
      "name": "OP_SETLIST",
      "scope": "public",
      "type": "int",
      "describe": [
        "static",
        "final"
      ]
    },
    {
      "name": "OP_CLOSE",
      "scope": "public",
      "type": "int",
      "describe": [
        "static",
        "final"
      ]
    },
    {
      "name": "OP_CLOSURE",
      "scope": "public",
      "type": "int",
      "describe": [
        "static",
        "final"
      ]
    },
    {
      "name": "OP_VARARG",
      "scope": "public",
      "type": "int",
      "describe": [
        "static",
        "final"
      ]
    },
    {
      "name": "NUM_OPCODES",
      "scope": "public",
      "type": "int",
      "describe": [
        "static",
        "final"
      ]
    },
    {
      "name": "int",
      "scope": "public",
      "type": "final",
      "describe": [
        "static"
      ]
    },
    {
      "name": "LFIELDS_PER_FLUSH",
      "scope": "public",
      "type": "int",
      "describe": [
        "static",
        "final"
      ]
    }
  ],
  "methods": [
    {
      "scope": "public",
      "describe": [
        "static"
      ],
      "return": "boolean",
      "name": "ISK",
      "args": [
        "int"
      ]
    },
    {
      "scope": "public",
      "describe": [
        "static"
      ],
      "return": "int",
      "name": "INDEXK",
      "args": [
        "int"
      ]
    },
    {
      "scope": "public",
      "describe": [
        "static"
      ],
      "return": "int",
      "name": "RKASK",
      "args": [
        "int"
      ]
    },
    {
      "scope": "public",
      "describe": [
        "static"
      ],
      "return": "int",
      "name": "getOpMode",
      "args": [
        "int"
      ]
    },
    {
      "scope": "public",
      "describe": [
        "static"
      ],
      "return": "int",
      "name": "getBMode",
      "args": [
        "int"
      ]
    },
    {
      "scope": "public",
      "describe": [
        "static"
      ],
      "return": "int",
      "name": "getCMode",
      "args": [
        "int"
      ]
    },
    {
      "scope": "public",
      "describe": [
        "static"
      ],
      "return": "boolean",
      "name": "testTMode",
      "args": [
        "int"
      ]
    }
  ]
}